friday/__init__.py
friday/agent/__init__.py
friday/agent/base_agent.py
friday/agent/friday_agent.py
friday/agent/prompt.py
friday/environment/__init__.py
friday/environment/bash_env.py
friday/environment/env.py
friday/environment/py_env.py
friday/tool_repository/__init__.py
friday/tool_repository/api_tools/__init__.py
friday/tool_repository/api_tools/audio2text/__init__.py
friday/tool_repository/api_tools/audio2text/audio2text.py
friday/tool_repository/api_tools/audio2text/audio2text_service.py
friday/tool_repository/api_tools/bing/__init__.py
friday/tool_repository/api_tools/bing/bing_api_v2.py
friday/tool_repository/api_tools/bing/bing_service.py
friday/tool_repository/api_tools/bing/image_search_api.py
friday/tool_repository/api_tools/bing/web_loader.py
friday/tool_repository/api_tools/image_caption/__init__.py
friday/tool_repository/api_tools/image_caption/gpt4v_caption.py
friday/tool_repository/api_tools/image_caption/image_caption_service.py
friday/tool_repository/api_tools/wolfram_alpha/__init__.py
friday/tool_repository/api_tools/wolfram_alpha/test.py
friday/tool_repository/api_tools/wolfram_alpha/wolfram_alpha.py
friday/tool_repository/basic_tools/__init__.py
friday/tool_repository/basic_tools/base_action.py
friday/tool_repository/basic_tools/get_os_version.py
friday/tool_repository/basic_tools/atom_action/__init__.py
friday/tool_repository/basic_tools/atom_action/operations/__init__.py
friday/tool_repository/basic_tools/atom_action/operations/coding.py
friday/tool_repository/basic_tools/atom_action/operations/files.py
friday/tool_repository/basic_tools/atom_action/operations/media.py
friday/tool_repository/basic_tools/atom_action/operations/routine.py
friday/tool_repository/basic_tools/atom_action/operations/system.py
friday/tool_repository/basic_tools/atom_action/query/__init__.py
friday/tool_repository/basic_tools/atom_action/query/device.py
friday/tool_repository/basic_tools/atom_action/query/files.py
friday_agent-0.1.0.dist-info/LICENSE
friday_agent-0.1.0.dist-info/METADATA
friday_agent-0.1.0.dist-info/WHEEL
friday_agent-0.1.0.dist-info/entry_points.txt
friday_agent-0.1.0.dist-info/top_level.txt
friday_agent-0.1.0.dist-info/RECORD
